README.md
setup.cfg
setup.py
/home/mikpom/ownCloud/src/python/lib/rbi_tree/rbi_tree/tree.cpp
rbi_tree/__init__.py
rbi_tree/intervaltree.hpp
rbi_tree/test_tree.py
rbi_tree/tree.cpp
rbi_tree/tree.pyx
rbi_tree.egg-info/PKG-INFO
rbi_tree.egg-info/SOURCES.txt
rbi_tree.egg-info/dependency_links.txt
rbi_tree.egg-info/not-zip-safe
rbi_tree.egg-info/top_level.txt