Metadata-Version: 2.1
Name: rbi-tree
Version: 0.2
Summary: Cython-wrapped C++ red-black interval tree implementation
Home-page: https://github.com/mikpom/rbi_tree
Author: @mikpom
Author-email: mikpom@mikpom.ru
License: MIT
Classifier: Programming Language :: Python :: 3
